patched_unittest
