Metadata-Version: 1.0
Name: patched-unittest
Version: 1.4
Summary: Automatically manage house-keeping for class level patching.
Home-page: https://github.com/ahammond/patched_unittest
Author: Andrew Hammond
Author-email: andrew.george.hammond@gmail.com
License: UNKNOWN
Platform: UNKNOWN
